dp_menu/__init__.py
dp_menu/frontend/build/asset-manifest.json
dp_menu/frontend/build/bootstrap.min.css
dp_menu/frontend/build/index.html
dp_menu/frontend/build/static/css/main.59363d86.css
dp_menu/frontend/build/static/css/main.59363d86.css.map
dp_menu/frontend/build/static/js/main.4f200308.js
dp_menu/frontend/build/static/js/main.4f200308.js.LICENSE.txt
dp_menu/frontend/build/static/js/main.4f200308.js.map
dp_menu_streamlit/__init__.py
dp_menu_streamlit/frontend/build/asset-manifest.json
dp_menu_streamlit/frontend/build/bootstrap.min.css
dp_menu_streamlit/frontend/build/index.html
dp_menu_streamlit/frontend/build/static/css/main.59363d86.css
dp_menu_streamlit/frontend/build/static/css/main.59363d86.css.map
dp_menu_streamlit/frontend/build/static/js/main.4f200308.js
dp_menu_streamlit/frontend/build/static/js/main.4f200308.js.LICENSE.txt
dp_menu_streamlit/frontend/build/static/js/main.4f200308.js.map
dp_menu_streamlit-0.0.1.dist-info/LICENSE
dp_menu_streamlit-0.0.1.dist-info/METADATA
dp_menu_streamlit-0.0.1.dist-info/WHEEL
dp_menu_streamlit-0.0.1.dist-info/top_level.txt
dp_menu_streamlit-0.0.1.dist-info/RECORD
